phis_login/LoginPage.py
phis_login/__init__.py
phis_login/default.yaml
phis_login/gui_error.py
phis_login/login_legacy_compat.py
phis_login/login_v2.py
phis_login/登录健康档案系统.py
phis_login/登录医生工作站.py
phis_login-2025.7.29.1.dist-info/METADATA
phis_login-2025.7.29.1.dist-info/WHEEL
phis_login-2025.7.29.1.dist-info/licenses/LICENSE
phis_login-2025.7.29.1.dist-info/RECORD
