Metadata-Version: 2.4
Name: phis-login
Version: 2025.7.29.1
Summary: auto login for PHIS
License-File: LICENSE
Requires-Python: >=3.12
Requires-Dist: ddddocr>=1.5.6
Requires-Dist: phis-config>=2025.7.29.3
Requires-Dist: pytest>=8.4.1
Requires-Dist: pyyaml>=6.0.2
Requires-Dist: soda-kapybara>=2025.7.28.0
